air_quality_index/__init__.py
air_quality_index/cli.py
air_quality_index-1.0.0.dist-info/LICENSE
air_quality_index-1.0.0.dist-info/METADATA
air_quality_index-1.0.0.dist-info/WHEEL
air_quality_index-1.0.0.dist-info/entry_points.txt
air_quality_index-1.0.0.dist-info/top_level.txt
air_quality_index-1.0.0.dist-info/RECORD
