Metadata-Version: 2.1
Name: air-quality-index
Version: 1.0.0
Summary: Download air quality index data from AirNow
Home-page: https://palewi.re/docs/air-quality-index/
Author: Ben Welsh
Author-email: b@palewi.re
License: MIT
Project-URL: Maintainer, https://github.com/datadesk
Project-URL: Source, https://github.com/datadesk/air-quality-index
Project-URL: Tracker, https://github.com/datadesk/air-quality-index/issues
Classifier: Development Status :: 5 - Production/Stable
Classifier: Programming Language :: Python
Classifier: Programming Language :: Python :: 3.9
Classifier: Programming Language :: Python :: 3.10
Classifier: Programming Language :: Python :: 3.11
Classifier: License :: OSI Approved :: MIT License
License-File: LICENSE
Requires-Dist: requests
Requires-Dist: click
Requires-Dist: kml2geojson
Requires-Dist: geojson
